marcuslion/DataGatewayInterface.py
marcuslion/__init__.py
marcuslion/apiUtils.py
marcuslion/config.py
marcuslion/dataframes.py
marcuslion/dataproviders.py
marcuslion/datasets.py
marcuslion/documents.py
marcuslion/indicators.py
marcuslion/mldataset.py
marcuslion/models.py
marcuslion/projects.py
marcuslion/providers.py
marcuslion/resources/marcus_lion_logo.jpg
marcuslion/restcontroller.py
marcuslion/resume.py
marcuslion/support.py
marcuslion/timeseries.py
marcuslion/ussec.py
marcuslion-0.2.56.dist-info/LICENSE
marcuslion-0.2.56.dist-info/METADATA
marcuslion-0.2.56.dist-info/WHEEL
marcuslion-0.2.56.dist-info/RECORD
